setup.py
carbondeploy/__init__.py
carbondeploy/client.py
carbondeploy/config.py
carbondeploy/errors.py
carbondeploy/json_utils.py
carbondeploy/thunk.py
carbondeploy.egg-info/PKG-INFO
carbondeploy.egg-info/SOURCES.txt
carbondeploy.egg-info/dependency_links.txt
carbondeploy.egg-info/requires.txt
carbondeploy.egg-info/top_level.txt
carbondeploy.egg-info/zip-safe