Metadata-Version: 1.2
Name: carbondeploy
Version: 1.1.0
Summary: Library for deploying Jupyter notebooks.
Home-page: https://www.carbondeploy.com/
Author: Michael Lucy
Author-email: michaelglucy@gmail.com
License: MIT
Platform: UNKNOWN
Requires-Python: >=3
